README.rst
m2websocket.py
setup.py
m2websocket.egg-info/PKG-INFO
m2websocket.egg-info/SOURCES.txt
m2websocket.egg-info/dependency_links.txt
m2websocket.egg-info/top_level.txt