Metadata-Version: 1.1
Name: m2websocket
Version: 0.1
Summary: Makes websockets with Mongrel2 and Python super easy
Home-page: http://github.com/Jaymon/m2websocket
Author: Jay Marcyes
Author-email: jay@marcyes.com
License: MIT
Platform: UNKNOWN
Classifier: Development Status :: 4 - Beta
Classifier: Environment :: Web Environment
Classifier: Intended Audience :: Developers
Classifier: License :: OSI Approved :: MIT License
Classifier: Operating System :: OS Independent
Classifier: Programming Language :: Python :: 2.7
Classifier: Topic :: Communications :: Chat
Classifier: Topic :: Internet :: WWW/HTTP
